linear_nonlinear_solver/__init__.py
linear_nonlinear_solver/bisection.py
linear_nonlinear_solver/cramer.py
linear_nonlinear_solver/gauss.py
linear_nonlinear_solver/gauss_jordan.py
linear_nonlinear_solver/gauss_seidel.py
linear_nonlinear_solver/jacobi.py
linear_nonlinear_solver/lu_decomposition.py
linear_nonlinear_solver-0.1.0.dist-info/LICENSE
linear_nonlinear_solver-0.1.0.dist-info/METADATA
linear_nonlinear_solver-0.1.0.dist-info/WHEEL
linear_nonlinear_solver-0.1.0.dist-info/RECORD
