Metadata-Version: 2.1
Name: linear-nonlinear-solver
Version: 0.1.0
Summary: una libreria para resolver ecuaciones lineales y no lineales usando metodos de ecuaciones.
Home-page: https://github.com/JeffreyMangandi/linear-nonlinear-solver
License: MIT
Keywords: linear,nonlinear,equations,solver,mathematics
Author: Jeffrey Mangandi
Author-email: jm21008@ues.edu.sv
Requires-Python: >=3.7,<4.0
Classifier: License :: OSI Approved :: MIT License
Classifier: Programming Language :: Python :: 3
Classifier: Programming Language :: Python :: 3.7
Classifier: Programming Language :: Python :: 3.8
Classifier: Programming Language :: Python :: 3.9
Classifier: Programming Language :: Python :: 3.10
Classifier: Programming Language :: Python :: 3.11
Classifier: Programming Language :: Python :: 3.12
Classifier: Programming Language :: Python :: 3.13
Project-URL: Repository, https://github.com/JeffreyMangandi/linear-nonlinear-solver
